<?xml version="1.0" encoding="UTF-8"?>
<!DOCTYPE xkbConfigRegistry SYSTEM "xkb.dtd">
<xkbConfigRegistry version="1.1">
  <modelList>
    <model>
      <configItem>
        <name>k7</name>
        <description>Keychron K7</description>
        <vendor>Keychron</vendor>
      </configItem>
    </model>
  </modelList>
  <layoutList>
    <layout>
      <configItem>
        <name>k7</name>
        <!-- Keyboard indicator for French layouts -->
        <shortDescription>fr</shortDescription>
        <description>French</description>
        <languageList>
          <iso639Id>fra</iso639Id>
        </languageList>
      </configItem>
    </layout>
  </layoutList>
</xkbConfigRegistry>

